apluggy/__about__.py
apluggy/__init__.py
apluggy/_decorator.py
apluggy/stack/__init__.py
apluggy/stack/aexit.py
apluggy/stack/async_.py
apluggy/stack/sync.py
apluggy/stack/types.py
apluggy/wrap/__init__.py
apluggy/wrap/ext.py
apluggy/wrap/main.py
apluggy-1.1.1.dist-info/METADATA
apluggy-1.1.1.dist-info/WHEEL
apluggy-1.1.1.dist-info/licenses/LICENSE.txt
apluggy-1.1.1.dist-info/RECORD
