Metadata-Version: 2.4
Name: apluggy
Version: 1.1.1
Summary: A wrapper of "pluggy" to support asyncio and context managers
Project-URL: Documentation, https://github.com/simonsobs/apluggy#readme
Project-URL: Issues, https://github.com/simonsobs/apluggy/issues
Project-URL: Source, https://github.com/simonsobs/apluggy
Author-email: Tai Sakuma <tai.sakuma@gmail.com>
License-Expression: MIT
License-File: LICENSE.txt
Classifier: Development Status :: 5 - Production/Stable
Classifier: Intended Audience :: Developers
Classifier: License :: OSI Approved :: MIT License
Classifier: Programming Language :: Python
Classifier: Programming Language :: Python :: 3.9
Classifier: Programming Language :: Python :: 3.10
Classifier: Programming Language :: Python :: 3.11
Classifier: Programming Language :: Python :: 3.12
Classifier: Programming Language :: Python :: 3.13
Classifier: Programming Language :: Python :: 3.14
Requires-Python: >=3.9
Requires-Dist: pluggy>=1.3
Requires-Dist: types-decorator>=5.1
Requires-Dist: typing-extensions>=4.12; python_version < '3.10'
Provides-Extra: tests
Requires-Dist: hypothesis>=6.117; extra == 'tests'
Requires-Dist: pytest-asyncio>=0.18; extra == 'tests'
Requires-Dist: pytest-cov>=3.0; extra == 'tests'
Requires-Dist: pytest-timeout>=2.1; extra == 'tests'
Requires-Dist: pytest>=8.0; extra == 'tests'
